README.md
setup.py
icon_etl.egg-info/PKG-INFO
icon_etl.egg-info/SOURCES.txt
icon_etl.egg-info/dependency_links.txt
icon_etl.egg-info/entry_points.txt
icon_etl.egg-info/requires.txt
icon_etl.egg-info/top_level.txt
iconetl/__init__.py
iconetl/csv_utils.py
iconetl/json_rpc_requests.py
iconetl/utils.py
iconetl/cli/__init__.py
iconetl/cli/export_all.py
iconetl/cli/export_blocks_and_transactions.py
iconetl/cli/export_receipts_and_logs.py
iconetl/cli/extract_csv_column.py
iconetl/cli/get_block_range_for_date.py
iconetl/cli/get_block_range_for_timestamps.py
iconetl/domain/__init__.py
iconetl/domain/block.py
iconetl/domain/receipt.py
iconetl/domain/receipt_log.py
iconetl/domain/transaction.py
iconetl/enumeration/__init__.py
iconetl/executors/__init__.py
iconetl/jobs/__init__.py
iconetl/jobs/export_all_common.py
iconetl/jobs/export_blocks_job.py
iconetl/jobs/export_receipts_job.py
iconetl/jobs/exporters/__init__.py
iconetl/jobs/exporters/blocks_and_transactions_item_exporter.py
iconetl/jobs/exporters/receipts_and_logs_item_exporter.py
iconetl/mappers/__init__.py
iconetl/mappers/block_mapper.py
iconetl/mappers/receipt_log_mapper.py
iconetl/mappers/receipt_mapper.py
iconetl/mappers/transaction_mapper.py
iconetl/misc/__init__.py
iconetl/misc/retriable_value_error.py
iconetl/providers/__init__.py
iconetl/providers/auto.py
iconetl/providers/rpc.py
iconetl/service/__init__.py
iconetl/service/graph_operations.py
iconetl/service/icx_service.py
iconetl/streaming/__init__.py
tests/iconetl/__init__.py
tests/iconetl/job/__init__.py
tests/iconetl/job/mock_batch_web3_provider.py
tests/iconetl/job/mock_web3_provider.py
tests/iconetl/job/test_export_blocks_job.py
tests/iconetl/job/test_export_receipts_job.py
tests/iconetl/job/utils.py
tests/iconetl/service/__init__.py
tests/iconetl/service/test_icx_service.py
tests/resources/__init__.py