Metadata-Version: 2.1
Name: icon-etl
Version: 0.1.1
Summary: Tools for exporting ICON blockchain data to CSV or JSON
Home-page: https://github.com/insight-icon/icon-etl
Author: Richard Mah
Author-email: richard@richardmah.com
License: UNKNOWN
Project-URL: Bug Reports, https://github.com/insight-icon/icon-etl/issues
Project-URL: Source, https://github.com/insight-icon/icon-etl
Platform: UNKNOWN
Classifier: Intended Audience :: Developers
Classifier: License :: OSI Approved :: MIT License
Classifier: Programming Language :: Python :: 3
Classifier: Programming Language :: Python :: 3.6
Classifier: Programming Language :: Python :: 3.7
Requires-Python: >=3.6.0,<3.8.0
Provides-Extra: streaming
Provides-Extra: dev
